layrzsimulator/__init__.py
layrzsimulator/charts.py
layrzsimulator/exceptions.py
layrzsimulator/messages.py
layrz_simulator-1.0.2.dist-info/LICENSE
layrz_simulator-1.0.2.dist-info/METADATA
layrz_simulator-1.0.2.dist-info/WHEEL
layrz_simulator-1.0.2.dist-info/top_level.txt
layrz_simulator-1.0.2.dist-info/RECORD
