Metadata-Version: 2.1
Name: layrz-simulator
Version: 1.0.2
Summary: Layrz Simulator
Home-page: https://gitlab.com/layrz-software/libraries/sdk-simulator
Author: Layrz
Author-email: software@layrz.com
License: MIT
Keywords: sdk goldenm lcl layrz compute language simulator
Classifier: Programming Language :: Python :: 3
Classifier: License :: OSI Approved :: MIT License
Classifier: Operating System :: OS Independent
Requires-Python: >=3.8
License-File: LICENSE
Requires-Dist: requests
Requires-Dist: pytz
Requires-Dist: matplotlib
Requires-Dist: layrz-sdk (>=1.1.0)
